<?xml version="1.0" encoding="utf-8" ?>
<dwsync>
<file name="accessibility.png" server="//10.8.0.1/c$/data/websites/common/" local="130714323053540000" remote="130714323050000000" />
<file name="appstore.png" server="//10.8.0.1/c$/data/websites/common/" local="130714323053630000" remote="130714323050000000" />
<file name="basics.png" server="//10.8.0.1/c$/data/websites/common/" local="130714323053760000" remote="130714323050000000" />
<file name="calculator.png" server="//10.8.0.1/c$/data/websites/common/" local="130714323053860000" remote="130714323050000000" />
<file name="calendar.png" server="//10.8.0.1/c$/data/websites/common/" local="130714323053960000" remote="130714323050000000" />
<file name="calendar2.png" server="//10.8.0.1/c$/data/websites/common/" local="130714323054060000" remote="130714323050000000" />
<file name="camera.png" server="//10.8.0.1/c$/data/websites/common/" local="130714323054160000" remote="130714323050000000" />
<file name="clock.png" server="//10.8.0.1/c$/data/websites/common/" local="130714323054260000" remote="130714323050000000" />
<file name="compass.png" server="//10.8.0.1/c$/data/websites/common/" local="130714323054340000" remote="130714323050000000" />
<file name="contacts.png" server="//10.8.0.1/c$/data/websites/common/" local="130714323054440000" remote="130714323050000000" />
<file name="help.png" server="//10.8.0.1/c$/data/websites/common/" local="130714323054540000" remote="130714323050000000" />
<file name="ipod.png" server="//10.8.0.1/c$/data/websites/common/" local="130714323054620000" remote="130714323050000000" />
<file name="itunes.png" server="//10.8.0.1/c$/data/websites/common/" local="130714323054710000" remote="130714323050000000" />
<file name="iwebkit.png" server="//10.8.0.1/c$/data/websites/common/" local="130714323054810000" remote="130714323050000000" />
<file name="mail.png" server="//10.8.0.1/c$/data/websites/common/" local="130714323054900000" remote="130714323050000000" />
<file name="maps.png" server="//10.8.0.1/c$/data/websites/common/" local="130714323055000000" remote="130714323050000000" />
<file name="messages.png" server="//10.8.0.1/c$/data/websites/common/" local="130714323055100000" remote="130714323050000000" />
<file name="music.png" server="//10.8.0.1/c$/data/websites/common/" local="130714323055200000" remote="130714323050000000" />
<file name="nike+.png" server="//10.8.0.1/c$/data/websites/common/" local="130714323055290000" remote="130714323050000000" />
<file name="notepad.png" server="//10.8.0.1/c$/data/websites/common/" local="130714323055380000" remote="130714323050000000" />
<file name="other.png" server="//10.8.0.1/c$/data/websites/common/" local="130714323055480000" remote="130714323050000000" />
<file name="otherapps.png" server="//10.8.0.1/c$/data/websites/common/" local="130714323055570000" remote="130714323050000000" />
<file name="photos.png" server="//10.8.0.1/c$/data/websites/common/" local="130714323055680000" remote="130714323050000000" />
<file name="plugin.png" server="//10.8.0.1/c$/data/websites/common/" local="130714323055770000" remote="130714323050000000" />
<file name="safari.png" server="//10.8.0.1/c$/data/websites/common/" local="130714323055870000" remote="130714323050000000" />
<file name="settings.png" server="//10.8.0.1/c$/data/websites/common/" local="130714323055960000" remote="130714323050000000" />
<file name="sketches.png" server="//10.8.0.1/c$/data/websites/common/" local="130714323056070000" remote="130714323050000000" />
<file name="sms.png" server="//10.8.0.1/c$/data/websites/common/" local="130714323056170000" remote="130714323050000000" />
<file name="start.png" server="//10.8.0.1/c$/data/websites/common/" local="130714323056260000" remote="130714323050000000" />
<file name="stocks.png" server="//10.8.0.1/c$/data/websites/common/" local="130714323056350000" remote="130714323050000000" />
<file name="telephone.png" server="//10.8.0.1/c$/data/websites/common/" local="130714323056450000" remote="130714323050000000" />
<file name="video.png" server="//10.8.0.1/c$/data/websites/common/" local="130714323056560000" remote="130714323050000000" />
<file name="voice.png" server="//10.8.0.1/c$/data/websites/common/" local="130714323056660000" remote="130714323050000000" />
<file name="weather.png" server="//10.8.0.1/c$/data/websites/common/" local="130714323056760000" remote="130714323050000000" />
<file name="wordpress.png" server="//10.8.0.1/c$/data/websites/common/" local="130714323056860000" remote="130714323050000000" />
<file name="youtube.png" server="//10.8.0.1/c$/data/websites/common/" local="130714323056970000" remote="130714323050000000" />
</dwsync>